{"_name":"oralb-fi_fi","_syndicationVersion":2,"display":{"10051":{"_internalCode":"10051","_sources":{"EverydaymeFI_FI":{"_sourceDisplayName":"a P&G website","_logoImageName":"https://photos-us.bazaarvoice.com/photo/2/cGhvdG86YXR0cmlidXRpb25sb2dvMg/a150e43b-df21-476a-b1de-e26f0956ab93","_summaryIcon":null,"_bannerIcon":null,"_displayOrder":2147483647,"_maxSyndicatedSummaries":0,"_contentConfigurations":{"REVIEW":{"_contentTruncationEnabled":false,"_showAttribution":true,"_showLogo":true,"_useAttributionLink":false,"_syndicationDisplayType":"INLINE","_showInSearchVoiceInlinePages":false}}}}},"10051-fi_fi":{"_internalCode":"10051-fi_fi","_sources":{"EverydaymeFI_FI":{"_sourceDisplayName":"a P&G website","_logoImageName":"https://photos-us.bazaarvoice.com/photo/2/cGhvdG86YXR0cmlidXRpb25sb2dvMg/a150e43b-df21-476a-b1de-e26f0956ab93","_summaryIcon":null,"_bannerIcon":null,"_displayOrder":2147483647,"_maxSyndicatedSummaries":0,"_contentConfigurations":{"REVIEW":{"_contentTruncationEnabled":false,"_showAttribution":true,"_showLogo":true,"_useAttributionLink":false,"_syndicationDisplayType":"INLINE","_showInSearchVoiceInlinePages":false}}}}}},"export":{"Gigantti-FI":{"_destinationClientName":"Gigantti-FI","_exportBean":"exportForSyndicationImportIncludePII","_includeLocales":["fi_FI"],"_scheduleName":"wholeWeekSchedule","_excludedContentCodesForExport":{"QUESTION":[],"REVIEW":["RET","PC","PRI","STP","CSN"]},"_moderationStatusesToExport":["APPROVED","REJECTED","REMOVEDBYCLIENT","EXPIRED"],"_syndicationDelayDays":0,"_numDays":30,"_generatorType":"INCREMENTAL","_generatorName":"oralb-fi_fi to Gigantti-FI - all-reviews-standard-client-internal-syndication-include-pii","_runFullUntil":null,"_runFullEvery":14,"_syndicationVersion":2,"_excludeLocales":[],"_contentTypes":["REVIEW"],"_includeInactiveProducts":true},"karkkainen":{"_destinationClientName":"karkkainen","_exportBean":"exportForSyndicationImportIncludePII","_includeLocales":["fi_FI"],"_scheduleName":"wholeWeekSchedule","_excludedContentCodesForExport":{"QUESTION":[],"REVIEW":["RET","PC","PRI","STP","CSN"]},"_moderationStatusesToExport":["APPROVED","REJECTED","REMOVEDBYCLIENT","EXPIRED"],"_syndicationDelayDays":0,"_numDays":30,"_generatorType":"INCREMENTAL","_generatorName":"oralb-fi_fi to karkkainen - all-reviews-standard-client-internal-syndication-include-pii","_runFullUntil":null,"_runFullEvery":14,"_syndicationVersion":2,"_excludeLocales":[],"_contentTypes":["REVIEW"],"_includeInactiveProducts":true},"Ellos-FI_FI":{"_destinationClientName":"Ellos-FI_FI","_exportBean":"exportForSyndicationImportIncludePII","_includeLocales":["fi_FI"],"_scheduleName":"wholeWeekSchedule","_excludedContentCodesForExport":{"QUESTION":[],"REVIEW":["RET","PC","PRI","STP","CSN"]},"_moderationStatusesToExport":["APPROVED","REJECTED","REMOVEDBYCLIENT","EXPIRED"],"_syndicationDelayDays":7,"_numDays":30,"_generatorType":"INCREMENTAL","_generatorName":"oralb-fi_fi to Ellos-FI_FI - all-reviews-standard-client-internal-syndication-include-pii","_runFullUntil":null,"_runFullEvery":7,"_syndicationVersion":2,"_excludeLocales":[],"_contentTypes":["REVIEW"],"_includeInactiveProducts":true}},"import":{"EverydaymeFI_FI":{"_sourceClientName":"EverydaymeFI_FI","_allowDuplicateContent":true,"_contextDataValueStrategy":"IMPORT_MATCHING","_includeClientResponses":false,"_includeRatingsOnlyReviews":false,"_keepFeatured":false,"_productMatchingStrategies":["SYNDICATION_MATCH_TABLE","EAN","UPC","ISBN","EXTERNAL_ID"],"_ratingDimensionsStrategy":"IMPORT_NONE","_videoImportStrategy":"VIDEO_EXTERNAL_ONLY","_includePhotos":false,"_excludedContentCodesForImport":["RET","PC","PRI","STP","CSN"],"_copyFamilyAttributesFromHostProduct":false,"_syndicationVersion":2,"_sendThroughModeration":false}},"portal":{"_enabledAnalystReports":[]}}
{"_name":"Cyberdefender","_syndicationVersion":2,"display":{},"export":{},"import":{},"portal":{"_enabledAnalystReports":[]}}
